xtr/__init__.py
xtr/example.py
te_xtr-0.0.1.dist-info/LICENSE
te_xtr-0.0.1.dist-info/METADATA
te_xtr-0.0.1.dist-info/WHEEL
te_xtr-0.0.1.dist-info/top_level.txt
te_xtr-0.0.1.dist-info/RECORD
