Metadata-Version: 2.1
Name: te-xtr
Version: 0.0.1
Summary: Technica Engineering Test Runner
Author-email: Technica Engineering GmbH <houssem.fantar@technica-engineering.de>
Project-URL: Homepage, https://github.com/hfantar/xtr
Project-URL: Issues, https://github.com/hfantar/xtr/issues
Classifier: Programming Language :: Python :: 3
Classifier: License :: OSI Approved :: MIT License
Classifier: Operating System :: OS Independent
Requires-Python: >=3.10
License-File: LICENSE
